MANIFEST.in
setup.py
django_template_bootstrap.egg-info/PKG-INFO
django_template_bootstrap.egg-info/SOURCES.txt
django_template_bootstrap.egg-info/dependency_links.txt
django_template_bootstrap.egg-info/not-zip-safe
django_template_bootstrap.egg-info/top_level.txt
template_bootstrap/__init__.py
template_bootstrap/locale/zh_CN/LC_MESSAGES/django.mo
template_bootstrap/locale/zh_CN/LC_MESSAGES/django.po
template_bootstrap/static/css/bootstrap-fontawesome.css
template_bootstrap/static/css/bootstrap-fontawesome.min.css
template_bootstrap/static/css/bootstrap-responsive.css
template_bootstrap/static/css/bootstrap-responsive.min.css
template_bootstrap/static/css/bootstrap.css
template_bootstrap/static/css/bootstrap.min.css
template_bootstrap/static/font/fontawesome-webfont.eot
template_bootstrap/static/font/fontawesome-webfont.svg
template_bootstrap/static/font/fontawesome-webfont.ttf
template_bootstrap/static/font/fontawesome-webfont.woff
template_bootstrap/static/img/glyphicons-halflings-white.png
template_bootstrap/static/img/glyphicons-halflings.png
template_bootstrap/static/js/bootstrap.js
template_bootstrap/static/js/bootstrap.min.js
template_bootstrap/static/js/bootstrap.min.jshint
template_bootstrap/static/js/jquery.js
template_bootstrap/static/js/template.js
template_bootstrap/templates/.template.html.swp
template_bootstrap/templates/404.html
template_bootstrap/templates/500.html
template_bootstrap/templates/base-fluid.html
template_bootstrap/templates/base-small.html
template_bootstrap/templates/base.html
template_bootstrap/templates/template-fluid.html
template_bootstrap/templates/template-sidebar.html
template_bootstrap/templates/template-small.html
template_bootstrap/templates/template.html
template_bootstrap/templates/bootstrap/layout/baseinput.html
template_bootstrap/templates/pagination/pagination.html