Metadata-Version: 1.0
Name: django-template-bootstrap
Version: 0.2.15
Summary: A django template based on twitter's bootstrap project.
Home-page: http://github.com/adieu/django-template-bootstrap
Author: Ivan Diao
Author-email: adieu@adieu.me
License: BSD
Platform: UNKNOWN
Classifier: Framework :: Django
Classifier: Intended Audience :: Developers
Classifier: Intended Audience :: System Administrators
Classifier: Operating System :: OS Independent
Classifier: Topic :: Software Development
